shellama/__init__.py
shellama/app.py
shellama/cli.py
shellama/debug_window.py
shellama/dir_ops.py
shellama/error_handler.py
shellama/file_ops.py
shellama/git_ops.py
shellama/logger.py
shellama/logging_config.py
shellama/routes/debug_routes.py
shellama/shell.py
shellama-0.1.13.dist-info/LICENSE
shellama-0.1.13.dist-info/METADATA
shellama-0.1.13.dist-info/WHEEL
shellama-0.1.13.dist-info/RECORD
