Metadata-Version: 2.3
Name: shellama
Version: 0.1.13
Summary: Shell and filesystem operations REST API service for the PyLama ecosystem
License: Apache-2.0
Author: Tom Sapletta
Author-email: info@example.com
Requires-Python: >=3.8,<4.0
Classifier: License :: OSI Approved :: Apache Software License
Classifier: Programming Language :: Python :: 3
Classifier: Programming Language :: Python :: 3.8
Classifier: Programming Language :: Python :: 3.9
Classifier: Programming Language :: Python :: 3.10
Classifier: Programming Language :: Python :: 3.11
Classifier: Programming Language :: Python :: 3.12
Classifier: Programming Language :: Python :: 3.13
Requires-Dist: flask (>=2.0.0,<3.0.0)
Requires-Dist: flask-cors (>=3.0.10,<4.0.0)
Requires-Dist: gitpython (>=3.1.0,<4.0.0)
Requires-Dist: pathlib (>=1.0.1,<2.0.0)
Requires-Dist: python-dotenv (>=0.19.0,<0.20.0)
Requires-Dist: requests (>=2.28.0,<3.0.0)
Project-URL: Repository, https://github.com/py-lama/shellama
